PyGine/BoxColliderComponent.py
PyGine/Camera.py
PyGine/CircleColliderComponent.py
PyGine/ColliderComponent.py
PyGine/Component.py
PyGine/Debug.py
PyGine/DefaultScene.py
PyGine/DrawCircleComponent.py
PyGine/DrawLineComponent.py
PyGine/DrawRectComponent.py
PyGine/DrawShapeComponent.py
PyGine/GameObject.py
PyGine/ImageLibrary.py
PyGine/KeyListener.py
PyGine/MouseListener.py
PyGine/Overlay.py
PyGine/PhysicCollisionModule.py
PyGine/PyGinegame.py
PyGine/Scene.py
PyGine/SpriteComponent.py
PyGine/TextComponent.py
PyGine/Transform.py
PyGine/Vector3.py
PyGine/__init__.py
PyGine-0.0.20.dist-info/LICENSE
PyGine-0.0.20.dist-info/METADATA
PyGine-0.0.20.dist-info/WHEEL
PyGine-0.0.20.dist-info/top_level.txt
PyGine-0.0.20.dist-info/RECORD
