Metadata-Version: 2.1
Name: PyGine
Version: 0.0.20
Summary: A simple 2D game engine
Author: PyGIne (Ronan.T)
Author-email: <ronan.tremoureux@gmail.com>
Keywords: python,game,engine,moteur,jeu,GameEngine,PyGine,PyGineGame,pygame,componentGame,component,gameEngine,game,engine,2D,2DGame,2DGameEngine,2DGameEnginePython,2DGameEnginePygame,2DGameEnginePyGine,PyGineGameEngine,PyGineGameEnginePython,PyGineGameEnginePygame,PyGineGameEnginePyGine
Classifier: Development Status :: 1 - Planning
Classifier: Intended Audience :: Developers
Classifier: Programming Language :: Python :: 3
Classifier: Operating System :: Unix
Classifier: Operating System :: MacOS :: MacOS X
Classifier: Operating System :: Microsoft :: Windows
License-File: LICENSE
Requires-Dist: pygame
